talk_to_lollms/__init__.py
talk_to_lollms/main.py
talk_to_lollms/assets/settings.svg
talk_to_lollms-0.1.9.dist-info/LICENSE
talk_to_lollms-0.1.9.dist-info/METADATA
talk_to_lollms-0.1.9.dist-info/WHEEL
talk_to_lollms-0.1.9.dist-info/entry_points.txt
talk_to_lollms-0.1.9.dist-info/top_level.txt
talk_to_lollms-0.1.9.dist-info/RECORD
